coalesce_mcp/__init__.py
coalesce_mcp/__main__.py
coalesce_mcp/client.py
coalesce_mcp/server.py
coalesce_mcp-0.1.3.dist-info/METADATA
coalesce_mcp-0.1.3.dist-info/WHEEL
coalesce_mcp-0.1.3.dist-info/entry_points.txt
coalesce_mcp-0.1.3.dist-info/licenses/LICENSE
coalesce_mcp-0.1.3.dist-info/RECORD
