Metadata-Version: 2.4
Name: coalesce-mcp
Version: 0.1.3
Summary: MCP server for Coalesce data pipeline investigation
Project-URL: Homepage, https://github.com/JarredR092699/coalesce-mcp
Project-URL: Repository, https://github.com/JarredR092699/coalesce-mcp
Project-URL: Issues, https://github.com/JarredR092699/coalesce-mcp/issues
Author-email: Jarred Robidoux <JarredRobidoux@gmail.com>
License: MIT
License-File: LICENSE
Keywords: ai,claude,coalesce,data-engineering,mcp
Classifier: Development Status :: 3 - Alpha
Classifier: Intended Audience :: Developers
Classifier: License :: OSI Approved :: MIT License
Classifier: Programming Language :: Python :: 3
Classifier: Programming Language :: Python :: 3.10
Classifier: Programming Language :: Python :: 3.11
Classifier: Programming Language :: Python :: 3.12
Requires-Python: >=3.10
Requires-Dist: httpx>=0.27.0
Requires-Dist: mcp>=1.0.0
